spiketraindist/__init__.py
spiketraindist/victor_purpura_dist.py
spiketraindist-0.0.1.dist-info/LICENSE
spiketraindist-0.0.1.dist-info/METADATA
spiketraindist-0.0.1.dist-info/WHEEL
spiketraindist-0.0.1.dist-info/RECORD
