Metadata-Version: 2.1
Name: spiketraindist
Version: 0.0.1
Summary: Calculate spike train distances
License: Unlicense
Keywords: temporal coding,metric space,dynamic programming,neuroscience,Spike train
Author: matrix-reloaded-zen
Author-email: zen@example.com
Requires-Python: >=3.9,<4.0
Classifier: License :: OSI Approved
Classifier: Programming Language :: Python :: 3
Classifier: Programming Language :: Python :: 3.9
Classifier: Programming Language :: Python :: 3.10
Classifier: Programming Language :: Python :: 3.11
Classifier: Programming Language :: Python :: 3.12
Requires-Dist: numba (>=0.60.0,<0.61.0)
Requires-Dist: numpy (>=1.26.0,<2.0.0)
